cakemix/__init__.py
cakemix/__main__.py
cakemix/cli.py
cakemix/commands/__init__.py
cakemix/commands/add.py
cakemix/commands/remove.py
cakemix/commands/run.py
cakemix/database.py
cakemix/output.py
cakemix_python-0.2.0.dist-info/entry_points.txt
cakemix_python-0.2.0.dist-info/LICENSE
cakemix_python-0.2.0.dist-info/WHEEL
cakemix_python-0.2.0.dist-info/METADATA
cakemix_python-0.2.0.dist-info/RECORD
